{
  "locations": [
    {
      "id": "loc_0_0_ac6b4110",
      "name": "Gloomfellkeep",
      "type": "town",
      "description": "A town known for its mysterious past",
      "x": 809,
      "y": 331,
      "dungeon_type": "dark_fantasy_caverns",
      "dungeon_level": 2,
      "features": [
        "Ancient Observatory",
        "Haunted Grounds"
      ],
      "services": [
        "Inn",
        "Blacksmith",
        "Market",
        "Temple",
        "Tavern"
      ],
      "image_url": "/static/world_images/loc-loc_0_0_ac6b4110.jpg",
      "discovered": false,
      "quests": []
    },
    {
      "id": "loc_0_1_e4c968e7",
      "name": "GloomPeak",
      "type": "mountain",
      "description": "A mountain known for its ancient guardians",
      "x": 275,
      "y": 509,
      "dungeon_type": "dark_fantasy_fortress",
      "dungeon_level": 1,
      "features": [
        "Ancient Observatory",
        "Sacred Spring"
      ],
      "services": [],
      "image_url": "/static/world_images/loc-loc_0_1_e4c968e7.jpg",
      "discovered": false,
      "quests": []
    },
    {
      "id": "loc_0_2_54cfdad6",
      "name": "Bonepeak Ruins",
      "type": "ruin",
      "description": "A ruin known for its dark secrets",
      "x": 876,
      "y": 94,
      "dungeon_type": "dark_fantasy_lair",
      "dungeon_level": 5,
      "features": [
        "Ancient Monument",
        "Haunted Grounds"
      ],
      "services": [],
      "image_url": "/static/world_images/loc-loc_0_2_54cfdad6.jpg",
      "discovered": false,
      "quests": []
    },
    {
      "id": "loc_0_3_3e370908",
      "name": "Ravenash",
      "type": "village",
      "description": "A village known for its dark secrets",
      "x": 131,
      "y": 288,
      "dungeon_type": "dark_fantasy_crypt",
      "dungeon_level": 4,
      "features": [
        "Forgotten Monument",
        "Cursed Spring"
      ],
      "services": [
        "Healer",
        "General Store",
        "Meeting Hall"
      ],
      "image_url": "/static/world_images/loc-loc_0_3_3e370908.jpg",
      "discovered": false,
      "quests": []
    },
    {
      "id": "loc_1_0_1bfcb5a7",
      "name": "Dreadscarkeep",
      "type": "town",
      "description": "A town known for its strategic importance",
      "x": 596,
      "y": 300,
      "dungeon_type": "dark_fantasy_caverns",
      "dungeon_level": 4,
      "features": [
        "Forgotten Monument",
        "Cursed Grounds"
      ],
      "services": [
        "Inn",
        "Blacksmith",
        "Market",
        "Temple",
        "Tavern"
      ],
      "image_url": "/static/world_images/loc-loc_1_0_1bfcb5a7.jpg",
      "discovered": false,
      "quests": []
    },
    {
      "id": "loc_1_1_d665a0c3",
      "name": "Blackfenrest",
      "type": "forest",
      "description": "A forest known for its dark secrets",
      "x": 117,
      "y": 266,
      "dungeon_type": "dark_fantasy_fortress",
      "dungeon_level": 2,
      "features": [
        "Hidden Monument",
        "Sacred Grounds"
      ],
      "services": [],
      "image_url": "/static/world_images/loc-loc_1_1_d665a0c3.jpg",
      "discovered": false,
      "quests": []
    },
    {
      "id": "loc_1_2_32d1a7b0",
      "name": "ViperSummit",
      "type": "mountain",
      "description": "A mountain known for its ancient guardians",
      "x": 647,
      "y": 458,
      "dungeon_type": "dark_fantasy_fortress",
      "dungeon_level": 2,
      "features": [
        "Ancient Observatory",
        "Sacred Woods"
      ],
      "services": [],
      "image_url": "/static/world_images/loc-loc_1_2_32d1a7b0.jpg",
      "discovered": false,
      "quests": []
    },
    {
      "id": "loc_1_3_2cd336d1",
      "name": "Crowwoundwatch",
      "type": "forest",
      "description": "A forest known for its ancient guardians",
      "x": 660,
      "y": 529,
      "dungeon_type": "dark_fantasy_fortress",
      "dungeon_level": 5,
      "features": [
        "Ancient Observatory",
        "Cursed Woods"
      ],
      "services": [],
      "image_url": "/static/world_images/loc-loc_1_3_2cd336d1.jpg",
      "discovered": false,
      "quests": []
    }
  ],
  "factions": [
    {
      "id": "fac_a0c85beb",
      "name": "Circle of Serpentgravewatch",
      "ideology": "Power-hungry cult seeking forbidden knowledge",
      "goals": [
        "Protect the relic",
        "Conquer Viperashspire"
      ],
      "relationships": {},
      "activities": []
    }
  ],
  "quests": [
    {
      "id": "quest_3410ce10",
      "title": "Gloomfellkeep's Secret",
      "description": "Investigate the ancient artifact in Gloomfellkeep",
      "objectives": [
        "Find clues in Gloomfellkeep",
        "Confront the beast",
        "Purify the artifact"
      ],
      "location_id": "loc_0_0_ac6b4110",
      "completed": false,
      "dungeon_required": true
    },
    {
      "id": "quest_413ca4bd",
      "title": "The Ashes of GloomPeak",
      "description": "Recover the ancient artifact in GloomPeak",
      "objectives": [
        "Find clues in GloomPeak",
        "Negotiate with the guardian",
        "Retrieve the relic"
      ],
      "location_id": "loc_0_1_e4c968e7",
      "completed": false,
      "dungeon_required": false
    },
    {
      "id": "quest_248ce4da",
      "title": "Bleak Reckoning",
      "description": "Recover the cursed relic in Bonepeak Ruins",
      "objectives": [
        "Decipher texts in Bonepeak Ruins",
        "Negotiate with the beast",
        "Retrieve the source"
      ],
      "location_id": "loc_0_2_54cfdad6",
      "completed": false,
      "dungeon_required": false
    },
    {
      "id": "quest_73134ac2",
      "title": "The Blackwatch Affair",
      "description": "Investigate the forbidden tome in Ravenash",
      "objectives": [
        "Gather allies in Ravenash",
        "Confront the beast",
        "Destroy the source"
      ],
      "location_id": "loc_0_3_3e370908",
      "completed": false,
      "dungeon_required": true
    },
    {
      "id": "quest_3ac3f801",
      "title": "The Gloomhollow Affair",
      "description": "Destroy the ancient artifact in Dreadscarkeep",
      "objectives": [
        "Decipher texts in Dreadscarkeep",
        "Negotiate with the guardian",
        "Retrieve the artifact"
      ],
      "location_id": "loc_1_0_1bfcb5a7",
      "completed": false,
      "dungeon_required": true
    },
    {
      "id": "quest_317370c0",
      "title": "Hidden Bone",
      "description": "Recover the ancient artifact in Blackfenrest",
      "objectives": [
        "Gather allies in Blackfenrest",
        "Confront the guardian",
        "Purify the source"
      ],
      "location_id": "loc_1_1_d665a0c3",
      "completed": false,
      "dungeon_required": true
    },
    {
      "id": "quest_569af66a",
      "title": "Bleak Reckoning: Chapter 1",
      "description": "Investigate the ancient artifact in ViperSummit",
      "objectives": [
        "Find clues in ViperSummit",
        "Evade the guardian",
        "Purify the relic"
      ],
      "location_id": "loc_1_2_32d1a7b0",
      "completed": false,
      "dungeon_required": true
    },
    {
      "id": "quest_1d3c681d",
      "title": "The Blood of Crowwoundwatch",
      "description": "Destroy the cursed relic in Crowwoundwatch",
      "objectives": [
        "Gather allies in Crowwoundwatch",
        "Evade the spirit",
        "Retrieve the relic"
      ],
      "location_id": "loc_1_3_2cd336d1",
      "completed": false,
      "dungeon_required": true
    }
  ],
  "seed": 42
}